<?xml version="1.0" encoding="utf-8"?>
<search>
  
  
  
  <entry>
    <title>利用SSH push 代码到仓库</title>
    <link href="/2020/12/11/%E5%88%A9%E7%94%A8SSH%20push%20%E4%BB%A3%E7%A0%81%E5%88%B0%E4%BB%93%E5%BA%93/"/>
    <url>/2020/12/11/%E5%88%A9%E7%94%A8SSH%20push%20%E4%BB%A3%E7%A0%81%E5%88%B0%E4%BB%93%E5%BA%93/</url>
    
    <content type="html"><![CDATA[<h3 id="首先配置SSH-KEY"><a href="#首先配置SSH-KEY" class="headerlink" title="首先配置SSH　KEY"></a>首先配置SSH　KEY</h3><p>具体可以参考这篇博客：<a href="https://www.jianshu.com/p/c9aa544a11d3">https://www.jianshu.com/p/c9aa544a11d3</a></p><h3 id="然后在terminal中"><a href="#然后在terminal中" class="headerlink" title="然后在terminal中"></a>然后在terminal中</h3><pre class=" language-hljs awk"><span class="hljs-regexp"><code class="language-hljs awk"><span class="hljs-regexp">//gi</span>t remote add XXX SSH ....git remote add ykq git@github.com:twtstudio/WePeiYang-Android.git<span class="hljs-regexp">//gi</span>t branch<span class="hljs-regexp">//</span>查看分支* announcement</code></pre><p>然后可以用</p><pre class=" language-hljs ebnf"><span class="hljs-attribute"><code class="language-hljs ebnf"><span class="hljs-attribute">git status -s</span></code></pre><p>查看是否已经add</p><p>然后</p><pre class=" language-hljs nginx"><span class="hljs-attribute">git</span> commit -m <span class="hljs-string"><code class="language-hljs nginx"><span class="hljs-attribute">git</span> commit -m <span class="hljs-string">"做了个人页面"</span></code></pre><pre class=" language-hljs armasm"><span class="hljs-symbol">git</span> <span class="hljs-keyword"><code class="language-hljs armasm"><span class="hljs-symbol">git</span> <span class="hljs-keyword">push</span> ykq announcement</code></pre><p>完成</p>]]></content>
    
    
    <categories>
      
      <category>-工具</category>
      
    </categories>
    
    
    <tags>
      
      <tag>-git</tag>
      
    </tags>
    
  </entry>
  
  
  
  <entry>
    <title>整数和浮点数</title>
    <link href="/2020/12/11/%E6%95%B4%E6%95%B0%E5%92%8C%E6%B5%AE%E7%82%B9%E6%95%B0/"/>
    <url>/2020/12/11/%E6%95%B4%E6%95%B0%E5%92%8C%E6%B5%AE%E7%82%B9%E6%95%B0/</url>
    
    <content type="html"><![CDATA[<h3 id="整数"><a href="#整数" class="headerlink" title="整数"></a>整数</h3><ul><li><p>编码方式</p><ul><li>原码</li><li>反码</li><li>补码（计算机内存中存储形式）</li></ul></li><li><p>表示方式</p><ul><li>十进制</li><li>八进制</li><li>十六进制</li></ul></li></ul><h3 id="浮点数"><a href="#浮点数" class="headerlink" title="浮点数"></a>浮点数</h3><ul><li><p>浮点格式</p><ul><li>单精度</li><li>双精度</li><li>精确度更高：java.math.BigDecimal</li></ul></li><li><p>IEEE浮点表示</p><ul><li>符号</li><li>尾数</li><li>阶码</li></ul></li><li><p>浮点数不能直接用==判等</p></li></ul>]]></content>
    
    
    <categories>
      
      <category>-编程</category>
      
    </categories>
    
    
    <tags>
      
      <tag>-基础知识</tag>
      
    </tags>
    
  </entry>
  
  
  
  <entry>
    <title>Java中static关键字的理解</title>
    <link href="/2020/09/16/Java%E4%B8%ADstatic%E5%85%B3%E9%94%AE%E5%AD%97%E7%9A%84%E7%90%86%E8%A7%A3/"/>
    <url>/2020/09/16/Java%E4%B8%ADstatic%E5%85%B3%E9%94%AE%E5%AD%97%E7%9A%84%E7%90%86%E8%A7%A3/</url>
    
    <content type="html"><![CDATA[<ul><li><p>static含义  static表示“静态的”，被static修饰的元素被称为“静态的“，都是<u>类级别</u>的特征，和具体对象无关。</p></li><li><p>static用途</p><ol><li><u><strong>修饰静态变量</strong></u>。（static绝对不可以修饰局部变量！）当不同对象的该变量相同时，可将该变量用static修饰，即定义为静态变量。</li></ol></li><li><p>静态变量与实例变量区别：<u>静态变量</u>存储在方法区内存中，在类加载时初始化（不需要创建对象，内存就开辟了）。可直接用”类名.“的方式访问。<u>实例变量</u>存储在栈内存中，一个Java对象有一份，属于Java对象，不同对象值不一定相同。只能通过对象才可以访问。</p></li></ul><ol start="2"><li><p><u><strong>修饰静态方法</strong></u>。静态方法是属于类的，如main方法。可在没有创建对象的情况下调用。可用”类名.“的方式访问（也可采用引用的方式访问，但即使采用引用的方式，实际上执行的时候也和引用指向的对象无关）。</p><ul><li><p>在静态方法内部不能直接访问实例变量和实例方法（必须通过具体的对象），反过来是可以滴。      </p>  <pre class=" language-hljs java"><span class="hljs-keyword">public</span> <span class="hljs-class"><span class="hljs-keyword">class</span> <span class="hljs-title"><code class="language-hljs java"><span class="hljs-keyword">public</span> <span class="hljs-class"><span class="hljs-keyword">class</span> <span class="hljs-title">Test01</span> </span>&#123;    <span class="hljs-function"><span class="hljs-keyword">public</span> <span class="hljs-keyword">static</span> <span class="hljs-keyword">void</span> <span class="hljs-title">name1</span><span class="hljs-params">(String name1)</span> </span>&#123;        name2();<span class="hljs-comment">//编译报错，因未创建对象直接访问</span>        System.out.println(name1);    &#125;    <span class="hljs-function"><span class="hljs-keyword">public</span> <span class="hljs-keyword">void</span> <span class="hljs-title">name2</span><span class="hljs-params">(String name2)</span></span>&#123;        name1(<span class="hljs-string">"啦啦啦"</span>);        System.out.println(name2);    &#125;</code></pre></li></ul></li></ol><ol start="3"><li><p><u><strong>定义”静态代码块“</strong></u>。</p><ul><li><p>”静态代码块“语法格式：</p>  <pre class=" language-hljs static&#123;&#125;"><code class="language-hljs static&#123;&#125;">static&#123;      java语句&#125;</code></pre><p>  在类加载时执行，并只执行一次，在一个类中可编写多个，自上而下依次执行。常用来完成预备工作，数据的准备工作。</p></li></ul></li></ol>]]></content>
    
    
    <categories>
      
      <category>-编程</category>
      
    </categories>
    
    
    <tags>
      
      <tag>-Java</tag>
      
    </tags>
    
  </entry>
  
  
  
  
</search>
